ipaas_sdk/__init__.py
ipaas_sdk/client.py
ipaas_sdk/credentials_manager.py
assetbridge_sdk-0.1.0.dist-info/LICENSE
assetbridge_sdk-0.1.0.dist-info/METADATA
assetbridge_sdk-0.1.0.dist-info/WHEEL
assetbridge_sdk-0.1.0.dist-info/top_level.txt
assetbridge_sdk-0.1.0.dist-info/RECORD
